cursor_deeplink/__init__.py
cursor_deeplink/cli.py
cursor_deeplink/deeplink.py
cursor_deeplink-0.1.1.dist-info/METADATA
cursor_deeplink-0.1.1.dist-info/WHEEL
cursor_deeplink-0.1.1.dist-info/entry_points.txt
cursor_deeplink-0.1.1.dist-info/top_level.txt
cursor_deeplink-0.1.1.dist-info/RECORD
