Metadata-Version: 2.4
Name: cursor-deeplink
Version: 0.1.1
Summary: A Python package for generating Cursor deeplinks for MCP server installation
Home-page: https://github.com/hemanth/cursor-deeplink
Author: Cursor Deeplink Generator
Author-email: 
License-Expression: MIT
Project-URL: Homepage, https://github.com/hemanth/cursor-deeplink
Project-URL: Bug Reports, https://github.com/hemanth/cursor-deeplink/issues
Project-URL: Source, https://github.com/hemanth/cursor-deeplink
Project-URL: Documentation, https://docs.cursor.com/deeplinks
Keywords: cursor,deeplink,mcp,server,installation
Classifier: Development Status :: 3 - Alpha
Classifier: Intended Audience :: Developers
Classifier: Operating System :: OS Independent
Classifier: Programming Language :: Python :: 3
Classifier: Programming Language :: Python :: 3.8
Classifier: Programming Language :: Python :: 3.9
Classifier: Programming Language :: Python :: 3.10
Classifier: Programming Language :: Python :: 3.11
Classifier: Programming Language :: Python :: 3.12
Classifier: Topic :: Software Development :: Libraries :: Python Modules
Classifier: Topic :: Utilities
Requires-Python: >=3.8
Provides-Extra: dev
Requires-Dist: pytest>=6.0; extra == "dev"
Requires-Dist: pytest-cov>=2.0; extra == "dev"
Requires-Dist: black>=21.0; extra == "dev"
Requires-Dist: flake8>=3.8; extra == "dev"
Requires-Dist: mypy>=0.900; extra == "dev"
Dynamic: home-page
Dynamic: requires-python
